{
 "mdsDat": {
 "x": [ 0.20759, 0.080041, -0.025874, 0.076426, -0.096222, 0.047557, 0.1331, -0.2001, 0.093831, -0.15177, 0.23875, -0.11651, -0.007357, -0.070392, -0.13595, -0.0010355, -0.072089 ],
"y": [ -0.11468, 0.28787, -0.059531, -0.075158, -0.078445, -0.048388, -0.069511, 0.038336, 0.28898, 0.037377, -0.071321, -0.10913, 0.027534, -0.069936, -0.0029729, -0.059668, 0.078647 ],
"topics": [ 1, 2, 3, 4, 5, 6, 7, 8, 9, 10, 11, 12, 13, 14, 15, 16, 17 ],
"Freq": [ 7.6623, 7.1309, 6.7426, 6.7164, 6.6554, 6.6466,  6.447, 6.3708, 5.6539, 5.5976, 5.5935, 5.5646, 5.1569,  4.927, 4.7456, 4.3409, 4.0482 ],
"cluster": [      1,      1,      1,      1,      1,      1,      1,      1,      1,      1,      1,      1,      1,      1,      1,      1,      1 ] 
},
"tinfo": {
 "Term": [ "brownlee", "gerry", "red", "world", "buildings", "cup", "aftershocks", "rugby", "key", "bob", "parker", "recovery", "council", "insurance", "john", "mayor", "people", "city", "zone", "newspaper", "government", "south", "damage", "rubble", "prime", "company", "disasters", "snow", "insurance", "quakes", "collapse", "cover", "floods", "heavy", "councils", "policies", "premiums", "south", "camping", "cancelled", "fires", "levy", "lightning", "otago", "receivership", "recently", "reinsurance", "scf", "weather", "port", "english", "billion", "million", "budget", "costs", "spending", "treasury", "card", "murray", "wallet", "act", "axe", "brown", "fund", "goff", "hobbit", "letter", "moved", "phil", "priority", "reach", "short", "tax", "events", "leader", "minutes", "nuclear", "tea", "bed", "silence", "tuesday", "affected", "catastrophe", "donations", "neighbour", "perspective", "television", "acc", "armchair", "baby", "board", "cricket", "crushed", "foreign", "planning", "remember", "septic", "sit", "smith", "team", "moon", "ken", "humour", "predictions", "latest", "mother", "shaking", "stress", "astrologer", "band", "drinking", "edge", "faction", "fleeing", "kids", "lunch", "planking", "predict", "prediction", "rolling", "spite", "volcanic", "ring", "december", "concern", "survivors", "debate", "heart", "rebuilt", "statue", "trapped", "community", "robert", "search", "strong", "anniversary", "capsule", "capsules", "date", "founder", "giant", "godley", "simply", "true", "urban", "printed", "arm", "spirit", "stone", "neighbours", "owners", "cordon", "allowed", "tape", "frustrated", "business", "happen", "issues", "owner", "premises", "security", "tools", "assessment", "awaited", "barrier", "beginning", "bounds", "burns", "demolished", "homeowners", "properties", "protest", "retrieve", "volcano", "wagner", "world", "rugby", "disaster", "stadium", "cup", "plastic", "rwc", "host", "venue", "accommodation", "break", "giving", "kiwifruit", "matches", "mud", "struggles", "thumbs", "waka", "pike", "mine", "holding", "decision", "amount", "suffered", "tv", "special", "published", "clown", "increase", "park", "replaced", "scale", "airport", "apology", "appointed", "international", "reported", "size", "tracks", "anglican", "calling", "declared", "mccully", "reaction", "star", "temporary", "tower", "worst", "lower", "version", "brownlee", "gerry", "recovery", "suburbs", "authority", "abandoned", "feet", "grand", "assets", "efforts", "empowers", "pointing", "sense", "suggesting", "cera", "hotel", "demolition", "due", "demolishing", "reconstruction", "cat", "lead", "friend", "asked", "signpost", "shipping", "container", "rock", "containers", "mobile", "architecture", "commission", "foundation", "future", "paid", "ship", "kit", "labeled", "merivale", "assessments", "brought", "builders", "contractors", "developed", "estate", "extra", "gas", "hour", "needed", "proof", "state", "bank", "repair", "reserve", "figure", "interest", "cardboard", "continue", "fault", "governor", "fissure", "milk", "ongoing", "recession", "roads", "shoulder", "wire", "balanced", "benchmark", "bollard", "cent", "headlines", "hits", "ho", "seismograph", "queue", "leaky", "rail", "risk", "talking", "explains", "shake", "announcement", "blah", "false", "gambling", "leaving", "simon", "wondering", "refugees", "men", "coming", "fence", "hands", "sign", "shop", "front", "stop", "heading", "interviewed", "portaloo", "portaloos", "sewage", "toilets", "driver", "check", "delhi", "live", "rubbish", "athletes", "commonwealth", "facilities", "pipes", "plumbing", "system", "bin", "candle", "clutching", "contents", "rats", "sewer", "thought", "truck", "tunnel", "sewerage", "colours", "green", "jersey", "streets", "wears", "yellow", "arrive", "blue", "chats", "evans", "parking", "politicians", "press", "prostitutes", "answers", "collapsing", "corner", "ears", "greener", "label", "late", "manchester", "newcomer", "stickered", "stops", "marryatt", "tony", "chief", "executive", "victims", "chim", "chimneys", "life", "dog", "money", "chamber", "advice", "commerce", "controversial", "deal", "form", "region", "result", "southland", "walk", "wave", "pay", "santa", "ceo", "massive", "series", "dalai", "father", "lama", "william", "harbour", "ideas", "pit", "royal", "visit", "dressed", "flush", "katene", "lamb", "pours", "referring", "ride", "sand", "trouble", "workman", "boy", "lyttelton", "prince", "pile", "build", "anderton", "body", "fight", "cracks", "jim", "gold", "mayoral", "win", "election", "profile", "shovel", "strike", "mp", "elections", "local", "bob", "move", "parker", "october", "aftermath", "coast", "cracked", "rival", "mayor", "helping", "island", "auckland", "rescue", "wife", "power", "eqc", "land", "key", "newspaper", "zone", "council", "japan", "access", "rate", "year", "john", "day", "central", "night", "headline", "walks", "husband", "continuing", "chemical", "kiwi", "orange", "great", "cost", "bill", "news", "march", "debris", "limbo", "aftershocks", "buildings", "areas", "public", "small", "crack", "crowd", "paper", "appears", "red", "river", "prime", "report", "claims", "rain", "reading", "voice", "place", "named", "assistance", "zones", "ami", "finance", "home", "standing", "government", "prime", "homes", "made", "rise", "face", "badly", "houses", "plan", "full", "conditions", "companies", "red", "economy", "shown", "flag", "replies", "called", "broken", "couple", "aftershock", "comments", "sits", "rubble", "games", "depicts", "word", "cathedral", "key", "includes", "words", "left", "nz", "buildings", "rubble", "tells", "north", "list", "group", "thinks", "tear", "background", "part", "district", "cbd", "title", "rebuild", "door", "large", "called", "word", "cathedral", "mayor", "people", "toilet", "cross", "earth", "financial", "fear", "children", "damaged", "ball", "fanzone", "arms", "powers", "house", "box", "toilet", "back", "cantabrians", "historic", "parts", "residential", "liquefaction", "deep", "words", "aftershocks", "residents", "wearing", "damage", "parker", "represents", "pm", "stand", "number", "city", "huge", "light", "liquefaction", "building", "homes", "tsunami", "chch", "representing", "council", "government", "black", "time", "june", "john", "car", "stands", "nature", "caused", "ball", "work", "infrastructure", "asks", "finance", "bob", "head", "building", "people", "point", "house", "city", "wearing", "chch", "cbd", "bill", "wonders", "shouts", "spade", "hit", "frames", "standing", "road", "dear", "today", "people", "city", "cut", "hit", "problems", "party", "representing", "damage", "city", "rebuild", "replies", "comments", "enormous", "announced", "rebuilding", "asks", "people", "problems", "workers", "ground", "people", "businesses", "ami", "rebuild", "large", "impact", "water", "back", "high", "working", "couple", "damage", "area", "suggests", "make", "damage", "week", "newspaper", "house", "big", "chch", "huge", "people", "june", "rebuilding", "city", "carrying", "city", "damaged", "broken", "announced", "week", "zone", "including", "show", "areas", "point", "tells", "hand", "ground", "rebuilding", "buildings", "time", "reading", "large", "people", "house", "residents", "liquefaction", "building", "representing", "large", "centre", "enormous", "frames", "residents", "months", "devastating", "map", "huge", "end", "big", "heritage", "pm", "government", "left", "rise", "part", "panel", "problems", "river", "representing", "huge", "represents", "holds", "work", "group", "back", "rebuilding", "sign", "ground", "road" ],
"logprob": [     25,     24,     23,     22,     21,     20,     19,     18,     17,     16,     15,     14,     13,     12,     11,     10,      9,      8,      7,      6,      5,      4,      3,      2,      1, -3.8198, -4.0018, -4.107, -2.7795, -4.2245, -4.5113, -4.5113, -4.5113, -4.5113, -4.9151, -4.9151, -4.9151, -3.1701, -5.2012, -5.2012, -5.2012, -5.2012, -5.2012, -5.2012, -5.2012, -5.2012, -5.2012, -5.2012, -4.107, -4.3577, -3.4607, -3.5941,  -3.93, -4.2858, -4.6211, -4.6211, -4.6211, -4.8433, -4.8433, -4.8433, -5.1293, -5.1293, -5.1293, -5.1293, -5.1293, -5.1293, -5.1293, -5.1293, -5.1293, -5.1293, -5.1293, -5.1293, -5.1293, -4.6211, -4.8433, -4.2335, -4.2335, -4.2335, -4.5688, -4.5688, -4.5688, -4.791, -4.791, -4.791, -4.791, -4.791, -4.791, -5.077, -5.077, -5.077, -5.077, -5.077, -5.077, -5.077, -5.077, -5.077, -5.077, -5.077, -5.077, -5.077, -3.5418, -3.6957, -3.7825, -3.9828, -4.2335, -4.2335, -4.2335, -4.3872, -4.5688, -4.5688, -5.077, -5.077, -5.077, -5.077, -5.077, -5.077, -5.077, -5.077, -5.077, -5.077, -5.077, -5.077, -3.4084, -4.5688, -4.791, -4.3789, -4.5605, -4.5605, -4.5605, -4.5605, -4.5605, -4.7827, -4.7827, -4.7827, -4.7827, -5.0687, -5.0687, -5.0687, -5.0687, -5.0687, -5.0687, -5.0687, -5.0687, -5.0687, -5.0687, -3.9745, -4.2252, -4.3789, -4.5605, -4.7827, -3.6769, -4.2147, -4.3684, -4.3684, -4.5501, -3.272, -4.7722, -4.7722, -4.7722, -4.7722, -4.7722, -4.7722, -5.0582, -5.0582, -5.0582, -5.0582, -5.0582, -5.0582, -5.0582, -5.0582, -5.0582, -5.0582, -5.0582, -5.0582, -5.0582, -2.4976, -2.6088, -3.5693, -3.9363, -2.5243, -4.5223, -4.5223, -4.7445, -4.7445, -5.0305, -5.0305, -5.0305, -5.0305, -5.0305, -5.0305, -5.0305, -5.0305, -5.0305, -3.736, -4.3407, -3.8312, -3.8312, -4.5223, -4.5223, -4.7445, -4.0429, -4.3298, -4.5114, -4.5114, -4.5114, -4.5114, -4.5114, -4.7336, -4.7336, -4.7336, -4.7336, -4.7336, -4.7336, -4.7336, -5.0196, -5.0196, -5.0196, -5.0196, -5.0196, -5.0196, -5.0196, -5.0196, -5.0196, -3.8203, -3.2905, -2.0768, -2.1584, -2.6071, -4.2139, -4.3956, -4.6177, -4.6177, -4.6177, -4.9038, -4.9038, -4.9038, -4.9038, -4.9038, -4.3956, -3.5224, -4.6177, -4.6177, -4.6177, -4.6177, -4.9038, -4.9038, -4.9038, -5.3059, -5.3059, -5.3059, -3.9197, -4.0528, -4.0528, -4.2065, -4.2065, -4.3882, -4.3882, -4.3882, -4.3882, -4.3882, -4.3882, -4.6103, -4.6103, -4.6103, -4.8964, -4.8964, -4.8964, -4.8964, -4.8964, -4.8964, -4.8964, -4.8964, -4.8964, -4.8964, -4.8964, -3.7997, -3.9172, -3.9172, -4.0504, -4.204, -4.204, -4.3857, -4.3857, -4.3857, -4.3857, -4.6079, -4.6079, -4.6079, -4.6079, -4.6079, -4.6079, -4.6079, -4.8939, -4.8939, -4.8939, -4.8939, -4.8939, -4.8939, -4.8939, -4.8939, -3.7947, -4.1991, -4.1991, -4.3807, -4.3807, -4.6029, -4.6029, -4.8889, -4.8889, -4.8889, -4.8889, -4.8889, -4.8889, -4.8889, -3.5076, -3.7947, -4.0454, -4.1991, -4.3807, -3.2848, -4.8889, -4.3807, -4.6029, -3.2203, -5.2911, -3.2124, -3.6172, -3.8399, -3.8399, -3.973, -4.3084, -4.3084, -4.3084, -4.3084, -4.5305, -4.5305, -4.5305, -4.5305, -4.5305, -4.5305, -4.8165, -4.8165, -4.8165, -4.8165, -4.8165, -4.8165, -4.8165, -4.8165, -4.8165, -4.5305, -3.9264, -3.9264, -4.0801, -4.0801, -4.0801, -4.2617, -4.4839, -4.4839, -4.4839, -4.4839, -4.4839, -4.4839, -4.4839, -4.4839, -4.7699, -4.7699, -4.7699, -4.7699, -4.7699, -4.7699, -4.7699, -4.7699, -4.7699, -4.7699, -4.7699, -3.0641, -3.3514, -3.756, -3.756, -3.8892, -4.0429, -4.0429, -4.0429, -4.2245, -4.2245, -4.4467, -4.7327, -4.7327, -4.7327, -4.7327, -4.7327, -4.7327, -4.7327, -4.7327, -4.7327, -4.7327, -3.1975, -4.2245, -4.4467, -4.4467, -3.9609, -4.1426, -4.1426, -4.1426, -4.1426, -4.3647, -4.3647, -4.3647, -4.3647, -4.3647, -4.6507, -4.6507, -4.6507, -4.6507, -4.6507, -4.6507, -4.6507, -4.6507, -4.6507, -4.6507, -3.5566, -3.9609, -3.9609, -4.3647, -4.3647, -3.4878, -3.4878, -3.6053, -3.8922, -4.0738, -4.296, -4.296, -4.296, -4.582, -4.582, -4.582, -4.582, -3.8922, -3.4878, -3.8922, -2.5084, -3.3827, -2.5509, -3.8922, -4.296, -4.9841, -4.9841, -4.9841, -2.6418, -4.582, -3.8198,  -3.93, -4.2252, -3.8777, -4.3807, -3.8022, -3.3896, -2.7999, -2.9626, -2.8306, -2.6591, -4.2335, -4.2147, -4.0504, -3.597, -2.7682, -4.1003, -3.6769, -4.1267, -3.7825, -4.5113, -4.3872, -3.7825, -4.204, -4.1003, -4.0815, -3.6946, -3.6681, -3.5941, -3.6158, -3.5418, -4.9038, -4.9038, -2.7804, -2.7076, -3.4754, -3.8892, -3.8072, -4.3577, -4.1761, -3.6946, -4.0504, -2.4405, -3.8312, -3.4607, -4.0815, -4.2245, -4.693, -3.4729, -4.3882, -4.3882, -4.2617, -4.2617, -4.2617, -3.9067, -3.5941, -3.697, -3.6053, -3.2891, -3.7044, -3.6769, -3.5994, -3.6385, -4.3872, -4.3789, -3.964, -4.3298, -4.2065, -4.1267, -4.3577, -2.9846, -4.0504, -4.0504, -3.9264, -3.7947, -3.6896, -3.6874, -3.8777, -3.8777, -3.8203, -4.2335, -3.6075, -4.187, -4.1761, -3.8777, -3.8694, -3.4425, -4.3298, -3.7638, -3.9363, -3.9197, -3.1027, -3.2694, -4.2139, -4.693, -4.693, -4.2335, -4.5688, -4.5688, -4.5605, -4.2147, -4.5501, -4.0815, -4.1761, -3.515, -4.3084, -3.6158, -3.8777, -3.9745, -3.9254, -3.5584, -2.7745, -3.7223, -4.8433, -4.8433, -4.8433, -4.791, -4.3872, -3.8694, -4.0538, -4.7445, -4.7445, -4.7336, -3.4351, -4.6103, -3.6946, -3.8399, -4.791, -4.7827, -4.5305, -4.4839, -3.4514, -4.3647, -4.0018, -3.1077, -3.7947, -4.0738, -3.4264, -3.6383, -3.9363, -4.4395, -4.4395, -4.1991, -3.0036, -4.0018, -4.3084, -3.9828, -3.8022, -3.9122, -4.3872, -4.0538, -3.9067, -3.6383, -3.6383, -3.9264, -4.1003, -3.964, -3.7044, -4.582, -4.2245, -4.5688, -4.2252, -4.2252, -4.2065, -4.3084, -3.8072, -4.107, -3.7251, -4.3956, -3.9122, -3.2905, -4.0504, -3.7223, -3.3886, -4.0801, -3.8892, -4.1761, -4.2139, -4.4467, -4.4467, -4.3647, -4.2858, -4.3872, -4.187, -3.9609, -4.5688, -4.5688, -3.5418, -3.5584, -4.3857, -4.2245, -4.0429, -4.6211, -3.9745, -3.6172, -3.4514, -3.8072, -3.9609, -4.2335, -4.3789, -4.3684, -4.0528, -4.1991, -3.6158, -3.973, -4.3789, -4.4395, -3.6874, -4.5501, -4.3407, -4.2858, -4.0815, -4.3857, -4.1426, -4.3956, -4.1267, -4.4839, -4.296, -3.9745, -4.5501, -4.3857, -4.3857, -4.0815, -4.1761, -3.973, -4.0801, -4.4467, -4.4395, -4.3956, -3.8022, -4.2245, -4.4395, -3.9745, -4.5223, -3.9122, -4.2065, -4.1267, -4.6211, -4.3872, -4.0801, -4.3882, -4.5223, -4.6177, -4.3807, -4.3084, -4.3084, -4.3084, -4.6177, -4.0801, -4.3789, -4.6177, -4.204, -4.2245, -4.3684, -4.2617, -4.2617, -4.3789, -4.5223, -4.3298, -4.5113, -4.5113, -4.6211, -4.5688, -4.5688, -4.5688, -4.5688, -4.5688, -4.5688, -4.5688, -4.5605, -4.5605, -4.5501, -4.5501, -4.5114, -4.5114, -4.5114, -4.3882, -4.3882, -4.3857, -4.3857, -4.3857, -4.3857, -4.4839, -4.4839, -4.7327, -4.3647, -4.582, -4.582, -4.582 ],
"loglift": [     25,     24,     23,     22,     21,     20,     19,     18,     17,     16,     15,     14,     13,     12,     11,     10,      9,      8,      7,      6,      5,      4,      3,      2,      1, 2.5428, 2.5377, 2.5343, 2.5311,   2.53, 2.5175, 2.5175, 2.5175, 2.5175, 2.4928, 2.4928, 2.4928, 2.4743, 2.4689, 2.4689, 2.4689, 2.4689, 2.4689, 2.4689, 2.4689, 2.4689, 2.4689, 2.4689, 2.4333, 2.3973, 2.6211, 2.6183, 2.6095, 2.5965, 2.5794, 2.5794, 2.5794, 2.5647, 2.5647, 2.5647, 2.5408, 2.5408, 2.5408, 2.5408, 2.5408, 2.5408, 2.5408, 2.5408, 2.5408, 2.5408, 2.5408, 2.5408, 2.5408, 2.4077, 2.3608, 2.6523, 2.6523, 2.6523, 2.6352, 2.6352, 2.6352, 2.6204, 2.6204, 2.6204, 2.6204, 2.6204, 2.6204, 2.5964, 2.5964, 2.5964, 2.5964, 2.5964, 2.5964, 2.5964, 2.5964, 2.5964, 2.5964, 2.5964, 2.5964, 2.5964,  2.678, 2.6743,  2.672, 2.6657,  2.656,  2.656,  2.656, 2.6488, 2.6388, 2.6388, 2.5999, 2.5999, 2.5999, 2.5999, 2.5999, 2.5999, 2.5999, 2.5999, 2.5999, 2.5999, 2.5999, 2.5999, 2.5645, 2.4676, 2.4186, 2.6579, 2.6479, 2.6479, 2.6479, 2.6479, 2.6479, 2.6331, 2.6331, 2.6331, 2.6331, 2.6089, 2.6089, 2.6089, 2.6089, 2.6089, 2.6089, 2.6089, 2.6089, 2.6089, 2.6089, 2.5733, 2.5364, 2.5113, 2.4761, 2.4277,  2.685, 2.6669, 2.6597, 2.6597, 2.6498, 2.6409, 2.6351, 2.6351, 2.6351, 2.6351, 2.6351, 2.6351, 2.6112, 2.6112, 2.6112, 2.6112, 2.6112, 2.6112, 2.6112, 2.6112, 2.6112, 2.6112, 2.6112, 2.6112, 2.6112, 2.7332, 2.7322, 2.7174, 2.7069, 2.6812, 2.6801, 2.6801, 2.6654, 2.6654, 2.6414, 2.6414, 2.6414, 2.6414, 2.6414, 2.6414, 2.6414, 2.6414, 2.6414,  2.629, 2.5443, 2.5349, 2.5337,  2.511, 2.5094, 2.4597, 2.7145, 2.7019, 2.6919, 2.6919, 2.6919, 2.6919, 2.6919, 2.6772, 2.6772, 2.6772, 2.6772, 2.6772, 2.6772, 2.6772, 2.6532, 2.6532, 2.6532, 2.6532, 2.6532, 2.6532, 2.6532, 2.6532, 2.6532, 2.6295, 2.4812, 2.8666,  2.866, 2.8622, 2.8211, 2.8111, 2.7963, 2.7963, 2.7963, 2.7722, 2.7722, 2.7722, 2.7722, 2.7722, 2.6396, 2.6275, 2.5894, 2.5877, 2.5877, 2.5876, 2.5111, 2.5105, 2.5087, 2.3708, 2.3706, 2.3706, 2.8436, 2.8382, 2.8382, 2.8309, 2.8309, 2.8209, 2.8209, 2.8209, 2.8209, 2.8209, 2.8209, 2.8061, 2.8061, 2.8061, 2.7819, 2.7819, 2.7819, 2.7819, 2.7819, 2.7819, 2.7819, 2.7819, 2.7819, 2.7819, 2.7819, 2.8487, 2.8444, 2.8444,  2.839, 2.8318, 2.8318, 2.8218, 2.8218, 2.8218, 2.8218,  2.807,  2.807,  2.807,  2.807,  2.807,  2.807,  2.807, 2.7828, 2.7828, 2.7828, 2.7828, 2.7828, 2.7828, 2.7828, 2.7828, 2.8539, 2.8369, 2.8369, 2.8269, 2.8269, 2.8121, 2.8121,  2.788,  2.788,  2.788,  2.788,  2.788,  2.788,  2.788, 2.7847, 2.7521, 2.7155, 2.6899,  2.654, 2.5383, 2.5267, 2.5092, 2.4341, 2.4301, 2.3892, 2.9437, 2.9333, 2.9256, 2.9256, 2.9201, 2.9028, 2.9028, 2.9028, 2.9028, 2.8879, 2.8879, 2.8879, 2.8879, 2.8879, 2.8879, 2.8637, 2.8637, 2.8637, 2.8637, 2.8637, 2.8637, 2.8637, 2.8637, 2.8637, 2.6818, 2.9657, 2.9657, 2.9585, 2.9585, 2.9585, 2.9485, 2.9336, 2.9336, 2.9336, 2.9336, 2.9336, 2.9336, 2.9336, 2.9336, 2.9094, 2.9094, 2.9094, 2.9094, 2.9094, 2.9094, 2.9094, 2.9094, 2.9094, 2.9094, 2.9094, 3.0281, 3.0216, 3.0087, 3.0087, 3.0032,  2.996,  2.996,  2.996, 2.9859, 2.9859, 2.9711, 2.9469, 2.9469, 2.9469, 2.9469, 2.9469, 2.9469, 2.9469, 2.9469, 2.9469, 2.9469, 2.8938, 2.8138, 2.7618, 2.7618, 3.0847, 3.0746, 3.0746, 3.0746, 3.0746, 3.0597, 3.0597, 3.0597, 3.0597, 3.0597, 3.0353, 3.0353, 3.0353, 3.0353, 3.0353, 3.0353, 3.0353, 3.0353, 3.0353, 3.0353, 2.9992, 2.9372, 2.9364, 2.8505, 2.8504, 3.1716, 3.1716, 3.1673, 3.1545, 3.1444, 3.1294, 3.1294, 3.1294,  3.105,  3.105,  3.105,  3.105, 3.0067, 2.9749, 2.8784, 2.8157, 2.7773, 2.7727, 2.7638, 2.7503, 2.6997, 2.6972, 2.6972, 2.6809, 2.6323,  2.395, 2.3564, 2.4246, 2.5727, 2.3793, 2.7452, 2.5237, 2.2854, 2.4418,  2.453, 2.6314, 2.5251, 2.5401, 2.7115, 2.3162,  2.252, 2.3533, 2.4695, 2.6404, 2.4351, 2.3712, 2.4997, 2.3071, 2.6858, 2.4437,  2.461, 2.5974, 2.3003, 2.2707, 2.3548, 2.3269, 2.3022, 2.3002, 2.1264, 2.1446, 2.6786, 2.6595, 2.7476, 2.2876, 2.4694, 2.5241, 2.6002, 2.4268, 2.2551, 2.1461, 2.3674, 2.2247,  2.337, 2.1751, 2.6489, 2.6478, 2.7782, 2.7758, 2.7751, 2.1164, 2.1312, 2.4561, 2.3179, 1.9943, 1.9024, 2.1885, 2.3752, 2.5816,  2.373,  2.382, 2.2506, 2.4292, 2.5564, 2.6385, 2.1829, 1.8827, 2.4947, 2.4941, 2.6215, 2.1292, 2.0865, 2.0464, 2.0959, 2.0932, 2.1495, 2.2175, 1.9716, 2.2654,  2.277, 2.0434, 2.0496, 1.6429, 2.3164, 1.9617, 2.0882,  2.299, 1.7496, 2.3096, 1.9391, 2.1941, 2.1906,  2.136, 2.3188, 2.3209, 2.3275, 2.1487, 2.3368, 2.0644, 2.1905, 2.0248, 2.5841, 1.7575, 1.8984, 1.9466, 1.9936, 1.7643, 1.5088,    2.2, 2.3592,  2.359, 2.3587, 2.4174, 2.1589, 1.8622,  2.033,  2.459, 2.4588, 2.4704, 1.8831, 2.5992, 2.2278, 2.2515, 2.4168, 2.4255, 2.6785, 2.7261, 2.2441,  2.849, 1.7237, 1.7991, 2.0283,  2.084, 1.5152, 1.6853, 1.8361, 2.0114, 2.0095, 2.2557, 1.6279, 1.6454, 2.4549, 1.7127, 1.8493, 1.9532, 2.1545, 1.7652, 1.5276, 1.6522, 1.6451, 2.1037, 1.8704, 1.7637, 1.3158,  2.312, 1.8009, 2.1941,  1.864, 1.8616, 2.0869, 2.3399, 2.1703, 1.6183, 1.5989, 1.9727, 1.7393, 0.9928, 2.1683, 1.5959, 1.2429, 2.0777, 1.9298, 1.9699, 1.6508, 2.5907, 2.5893,  2.677,  1.628, 1.9021, 1.7362, 2.1327, 2.3185, 2.3168, 0.7416, 1.0731, 2.5032, 1.6893, 1.6895, 2.0258, 1.4598, 1.3244,   1.18, 1.7326,  1.963, 1.7363, 1.9879, 1.9942, 1.7237, 1.7784, 0.6676, 1.7594, 1.9147, 1.5908, 0.5959, 2.2053, 1.6825,  1.254, 1.2917, 2.3742, 2.2287, 1.6957, 1.9648, 2.2778, 1.6776, 0.9671,  2.093, 2.2636, 2.2631, 0.8601, 1.8502, 1.4313, 1.2382, 2.2032, 1.3796, 1.2517, 0.4812, 1.5033, 1.3371,  0.657, 1.7672, 0.7192,  1.525,  1.607, 1.7415, 1.6391, 1.2035, 1.9031, 1.6943, 1.5364, 1.8379, 1.8447, 1.7809, 1.7219, 1.1588, 0.7722, 1.5918, 1.0303, 1.1692, 0.0588, 0.9498, 1.5612, 1.4338, 1.2726,  0.912, 1.0435, 1.7755, 1.8554, 1.6681, 1.2542, 1.7982,  2.079, 2.0763, 1.0784, 1.9778,  2.081, 1.8958, 1.8904, 0.7333, 1.4745, 1.7087,  1.852,  2.133, 1.3442, 1.6981, 1.0487, 1.2615, 1.3867,  1.982, 1.8095, 1.8856, 1.3586, 1.4119, 1.2411, 1.4483, 1.5117 ],
"Freq": [     49,     45,     52,     36,     53,     37,     50,     32,     42,     33,     33,     28,     34,     33,     45,     33,     94,     66,     34,     30,     34,     24,     49,     25,     25, 11.553, 9.6306, 8.6695, 32.698, 7.7083, 5.7861, 5.7861, 5.7861, 5.7861, 3.8638, 3.8638, 3.8638, 22.125, 2.9026, 2.9026, 2.9026, 2.9026, 2.9026, 2.9026, 2.9026, 2.9026, 2.9026, 2.9026, 8.6695, 6.7472, 15.397, 13.475, 9.6304,  6.747, 4.8248, 4.8248, 4.8248, 3.8637, 3.8637, 3.8637, 2.9026, 2.9026, 2.9026, 2.9026, 2.9026, 2.9026, 2.9026, 2.9026, 2.9026, 2.9026, 2.9026, 2.9026, 2.9026, 4.8248, 3.8637, 6.7224, 6.7224, 6.7224, 4.8072, 4.8072, 4.8072, 3.8496, 3.8496, 3.8496, 3.8496, 3.8496, 3.8496,  2.892,  2.892,  2.892,  2.892,  2.892,  2.892,  2.892,  2.892,  2.892,  2.892,  2.892,  2.892,  2.892, 13.373, 11.466, 10.512,  8.604, 6.6962, 6.6962, 6.6962, 5.7423, 4.7885, 4.7885, 2.8807, 2.8807, 2.8807, 2.8807, 2.8807, 2.8807, 2.8807, 2.8807, 2.8807, 2.8807, 2.8807, 2.8807, 15.281, 4.7885, 3.8346, 5.7376, 4.7845, 4.7845, 4.7845, 4.7845, 4.7845, 3.8314, 3.8314, 3.8314, 3.8314, 2.8783, 2.8783, 2.8783, 2.8783, 2.8783, 2.8783, 2.8783, 2.8783, 2.8783, 2.8783, 8.5968, 6.6907, 5.7376, 4.7845, 3.8314, 11.561, 6.7521, 5.7903, 5.7903, 4.8284, 17.332, 3.8666, 3.8666, 3.8666, 3.8666, 3.8666, 3.8666, 2.9048, 2.9048, 2.9048, 2.9048, 2.9048, 2.9048, 2.9048, 2.9048, 2.9048, 2.9048, 2.9048, 2.9048, 2.9048, 36.469, 32.632, 12.489, 8.6521,  35.51, 4.8153, 4.8153,  3.856,  3.856, 2.8968, 2.8968, 2.8968, 2.8968, 2.8968, 2.8968, 2.8968, 2.8968, 2.8968, 10.571, 5.7745, 9.6113, 9.6113, 4.8153, 4.8153,  3.856,  7.685, 5.7686, 4.8103, 4.8103, 4.8103, 4.8103, 4.8103, 3.8521, 3.8521, 3.8521, 3.8521, 3.8521, 3.8521, 3.8521, 2.8939, 2.8939, 2.8939, 2.8939, 2.8939, 2.8939, 2.8939, 2.8939, 2.8939, 9.6015, 16.309, 48.717, 44.898, 28.665, 5.7483, 4.7934, 3.8385, 3.8385, 3.8385, 2.8837, 2.8837, 2.8837, 2.8837, 2.8837, 4.7934, 11.477, 3.8385, 3.8385, 3.8385, 3.8385, 2.8837, 2.8837, 2.8837, 1.9288, 1.9288, 1.9288,  7.638, 6.6856, 6.6856, 5.7332, 5.7332, 4.7809, 4.7809, 4.7809, 4.7809, 4.7809, 4.7809, 3.8285, 3.8285, 3.8285, 2.8761, 2.8761, 2.8761, 2.8761, 2.8761, 2.8761, 2.8761, 2.8761, 2.8761, 2.8761, 2.8761, 8.6054, 7.6513, 7.6513, 6.6973, 5.7433, 5.7433, 4.7892, 4.7892, 4.7892, 4.7892, 3.8352, 3.8352, 3.8352, 3.8352, 3.8352, 3.8352, 3.8352, 2.8812, 2.8812, 2.8812, 2.8812, 2.8812, 2.8812, 2.8812, 2.8812, 8.6036, 5.7421, 5.7421, 4.7883, 4.7883, 3.8344, 3.8344, 2.8806, 2.8806, 2.8806, 2.8806, 2.8806, 2.8806, 2.8806, 11.465, 8.6036,  6.696, 5.7421, 4.7883, 14.327, 2.8806, 4.7883, 3.8344, 15.281, 1.9268, 14.273, 9.5219, 7.6213, 7.6213,  6.671, 4.7705, 4.7705, 4.7705, 4.7705, 3.8202, 3.8202, 3.8202, 3.8202, 3.8202, 3.8202, 2.8699, 2.8699, 2.8699, 2.8699, 2.8699, 2.8699, 2.8699, 2.8699, 2.8699, 3.8202,  6.678,  6.678, 5.7267, 5.7267, 5.7267, 4.7754, 3.8241, 3.8241, 3.8241, 3.8241, 3.8241, 3.8241, 3.8241, 3.8241, 2.8729, 2.8729, 2.8729, 2.8729, 2.8729, 2.8729, 2.8729, 2.8729, 2.8729, 2.8729, 2.8729, 15.235, 11.431, 7.6269, 7.6269, 6.6759, 5.7249, 5.7249, 5.7249, 4.7739, 4.7739, 3.8229,  2.872,  2.872,  2.872,  2.872,  2.872,  2.872,  2.872,  2.872,  2.872,  2.872, 13.333, 4.7739, 3.8229, 3.8229,  5.684, 4.7398, 4.7398, 4.7398, 4.7398, 3.7956, 3.7956, 3.7956, 3.7956, 3.7956, 2.8514, 2.8514, 2.8514, 2.8514, 2.8514, 2.8514, 2.8514, 2.8514, 2.8514, 2.8514, 8.5166,  5.684,  5.684, 3.7956, 3.7956, 8.5074, 8.5074, 7.5643, 5.6779, 4.7347, 3.7916, 3.7916, 3.7916, 2.8484, 2.8484, 2.8484, 2.8484, 5.6779, 8.5074, 5.6779, 22.655, 9.4506, 21.712, 5.6779, 3.7916, 1.9052, 1.9052, 1.9052, 19.826, 2.8484, 11.553, 9.6304, 6.6907, 9.5952, 4.7883, 8.5903, 15.409, 29.814, 23.959, 26.951, 22.843, 6.7224, 6.7521, 6.6973, 14.436, 30.775, 7.6501, 11.561, 5.7207, 10.553, 5.7861, 5.7648, 10.512, 5.7433,   7.68,  7.714, 9.5594, 12.514, 13.475, 12.468, 13.426, 2.8837, 2.8837, 28.635, 30.518, 10.483, 6.6759, 6.6282, 6.7472, 6.7268, 9.5594, 6.6973, 29.509, 9.6113, 15.397,  7.714, 7.7083, 4.8249, 14.383, 4.7809, 4.7809, 4.7754, 4.7754, 4.7754, 10.592, 13.475, 9.5427, 7.5643,  18.28, 9.5677, 11.561, 10.513, 8.5778, 5.7423, 5.7376, 8.6758, 5.7686, 5.7332, 5.7207, 6.7472, 23.103, 6.6973, 6.6973,  6.678, 8.6036, 9.5575, 11.456, 9.5952, 9.5578, 9.6015, 6.7224, 12.409, 6.7337, 6.7268, 9.5578, 9.5499, 12.432, 5.7686, 10.599, 8.6521,  7.638, 17.188, 11.349, 5.7483, 4.8249, 4.8249, 6.7224, 4.8072, 4.7885, 4.7845, 6.7521, 4.8284,  7.714, 6.7268, 11.447, 4.7705, 12.419, 9.5578, 8.5968, 8.6433, 12.476, 23.865, 8.5716, 3.8637, 3.8637, 3.8637, 3.8346, 5.7423, 9.5499, 7.6929,  3.856,  3.856, 3.8521,   12.4, 3.8285, 9.5594, 7.6213, 3.8346, 3.8314, 3.8202, 3.8241, 9.4608, 3.7956, 9.6306, 17.192, 8.6036, 4.7347, 14.407, 11.518, 8.6521, 5.7859, 5.7859, 5.7421, 16.186, 9.6306, 4.7705,  8.604, 8.5903, 7.6498, 5.7648, 7.6929, 10.592, 11.518, 11.518,  6.678,   7.68, 8.6758, 9.5677, 2.8484, 7.7083, 4.7885, 6.6907, 6.6907, 5.7332, 4.7705, 6.6282, 8.6695,  10.56, 4.7934, 7.6498, 16.309, 6.6973, 8.5716, 11.434, 5.7267, 6.6759, 6.7268, 5.7483, 3.8229, 3.8229, 3.7956,  6.747, 5.7423, 6.7337,  5.684, 4.8072, 4.8072, 13.373, 12.476, 4.7892, 7.7083,  7.685, 4.8248, 8.5968, 9.5219, 9.4608, 6.6282,  5.684, 6.7224, 5.7376, 5.7903, 6.6856, 5.7421, 12.468,  6.671, 5.7376, 5.7859, 11.456, 4.8284, 5.7745,  6.747,  7.714, 4.7892, 4.7398, 4.7934, 5.7207, 3.8241, 3.7916, 8.5968, 4.8284, 4.7892, 4.7892,  7.714, 6.7268,  6.671, 5.7267, 3.8229, 5.7859, 4.7934, 8.5903, 7.7083, 5.7859, 8.5968, 4.8153, 7.6498, 5.7332, 5.7207, 4.8248, 5.7648, 5.7267, 4.7809, 4.8153, 3.8385, 4.7883, 4.7705, 4.7705, 4.7705, 3.8385, 5.7267, 5.7376, 3.8385, 5.7433, 4.7739, 5.7903, 4.7754, 4.7754, 5.7376, 4.8153, 5.7686, 5.7861, 5.7861, 4.8248, 4.8072, 4.8072, 4.8072, 4.8072, 4.7885, 4.7885, 4.7885, 4.7845, 4.7845, 4.8284, 4.8284, 4.8103, 4.8103, 4.8103, 4.7809, 4.7809, 4.7892, 4.7892, 4.7892, 4.7892, 3.8241, 3.8241,  2.872, 3.7956, 2.8484, 2.8484, 2.8484 ],
"Total": [     49,     45,     52,     36,     53,     37,     50,     32,     42,     33,     33,     28,     34,     33,     45,     33,     94,     66,     34,     30,     34,     24,     49,     25,     25, 11.858, 9.9358, 8.9747, 33.957, 8.0135, 6.0913, 6.0913, 6.0913, 6.0913,  4.169,  4.169,  4.169, 24.319, 3.2078, 3.2078, 3.2078, 3.2078, 3.2078, 3.2078, 3.2078, 3.2078, 3.2078, 3.2078, 9.9285,   8.01, 15.702,  13.78, 9.9356, 7.0522,   5.13,   5.13,   5.13, 4.1689, 4.1689, 4.1689, 3.2078, 3.2078, 3.2078, 3.2078, 3.2078, 3.2078, 3.2078, 3.2078, 3.2078, 3.2078, 3.2078, 3.2078, 3.2078, 6.0911, 5.1121, 7.0276, 7.0276, 7.0276, 5.1124, 5.1124, 5.1124, 4.1548, 4.1548, 4.1548, 4.1548, 4.1548, 4.1548, 3.1972, 3.1972, 3.1972, 3.1972, 3.1972, 3.1972, 3.1972, 3.1972, 3.1972, 3.1972, 3.1972, 3.1972, 3.1972, 13.679, 11.771, 10.817, 8.9093, 7.0016, 7.0016, 7.0016, 6.0477, 5.0938, 5.0938, 3.1861, 3.1861, 3.1861, 3.1861, 3.1861, 3.1861, 3.1861, 3.1861, 3.1861, 3.1861, 3.1861, 3.1861,  17.51, 6.0448, 5.0841, 6.0429, 5.0899, 5.0899, 5.0899, 5.0899, 5.0899, 4.1368, 4.1368, 4.1368, 4.1368, 3.1837, 3.1837, 3.1837, 3.1837, 3.1837, 3.1837, 3.1837, 3.1837, 3.1837, 3.1837, 9.8532, 7.9571,  6.997, 6.0437, 5.0799, 11.867, 7.0573, 6.0955, 6.0955, 5.1336, 18.592, 4.1718, 4.1718, 4.1718, 4.1718, 4.1718, 4.1718, 3.2099, 3.2099, 3.2099, 3.2099, 3.2099, 3.2099, 3.2099, 3.2099, 3.2099, 3.2099, 3.2099, 3.2099, 3.2099, 36.775, 32.938, 12.794, 8.9573, 37.718, 5.1205, 5.1205, 4.1613, 4.1613, 3.2021, 3.2021, 3.2021, 3.2021, 3.2021, 3.2021, 3.2021, 3.2021, 3.2021,  11.83, 7.0335, 11.817, 11.832, 6.0637, 6.0736, 5.1116, 7.9903, 6.0738, 5.1156, 5.1156, 5.1156, 5.1156, 5.1156, 4.1574, 4.1574, 4.1574, 4.1574, 4.1574, 4.1574, 4.1574, 3.1991, 3.1991, 3.1991, 3.1991, 3.1991, 3.1991, 3.1991, 3.1991, 3.1991, 10.869, 21.412, 49.022, 45.203,  28.97, 6.0536, 5.0987, 4.1439, 4.1439, 4.1439,  3.189,  3.189,  3.189,  3.189,  3.189, 6.0526, 14.668, 5.0962,  5.105,  5.105, 5.1057, 4.1403,  4.143, 4.1501, 3.1865, 3.1872, 3.1872, 7.9434,  6.991,  6.991, 6.0386, 6.0386, 5.0863, 5.0863, 5.0863, 5.0863, 5.0863, 5.0863, 4.1339, 4.1339, 4.1339, 3.1815, 3.1815, 3.1815, 3.1815, 3.1815, 3.1815, 3.1815, 3.1815, 3.1815, 3.1815, 3.1815, 8.9107, 7.9567, 7.9567, 7.0027, 6.0486, 6.0486, 5.0946, 5.0946, 5.0946, 5.0946, 4.1406, 4.1406, 4.1406, 4.1406, 4.1406, 4.1406, 4.1406, 3.1865, 3.1865, 3.1865, 3.1865, 3.1865, 3.1865, 3.1865, 3.1865,  8.909, 6.0475, 6.0475, 5.0936, 5.0936, 4.1398, 4.1398, 3.1859, 3.1859, 3.1859, 3.1859, 3.1859, 3.1859, 3.1859, 12.723, 9.8639, 7.9624, 7.0051, 6.0555, 20.339, 4.1372, 6.9984, 6.0417, 24.174, 3.1753, 14.579, 9.8273, 7.9267, 7.9267, 6.9764, 5.0759, 5.0759, 5.0759, 5.0759, 4.1256, 4.1256, 4.1256, 4.1256, 4.1256, 4.1256, 3.1753, 3.1753, 3.1753, 3.1753, 3.1753, 3.1753, 3.1753, 3.1753, 3.1753, 5.0698, 6.9834, 6.9834, 6.0321, 6.0321, 6.0321, 5.0808, 4.1295, 4.1295, 4.1295, 4.1295, 4.1295, 4.1295, 4.1295, 4.1295, 3.1783, 3.1783, 3.1783, 3.1783, 3.1783, 3.1783, 3.1783, 3.1783, 3.1783, 3.1783, 3.1783,  15.54, 11.736, 7.9323, 7.9323, 6.9813, 6.0303, 6.0303, 6.0303, 5.0793, 5.0793, 4.1283, 3.1774, 3.1774, 3.1774, 3.1774, 3.1774, 3.1774, 3.1774, 3.1774, 3.1774, 3.1774, 15.555, 6.0332, 5.0895, 5.0895, 5.9895, 5.0454, 5.0454, 5.0454, 5.0454, 4.1012, 4.1012, 4.1012, 4.1012, 4.1012,  3.157,  3.157,  3.157,  3.157,  3.157,  3.157,  3.157,  3.157,  3.157,  3.157, 9.7759, 6.9419, 6.9471, 5.0552,  5.056,  8.813,  8.813, 7.8698, 5.9835, 5.0403, 4.0971, 4.0971, 4.0971, 3.1539, 3.1539, 3.1539, 3.1539, 6.9366, 10.729,  7.886, 33.501, 14.523, 33.516, 8.8433, 5.9855, 3.1639, 3.1719, 3.1719, 33.549, 5.0601, 13.746, 12.798, 8.8986, 10.862, 7.9698, 9.8576, 18.584, 42.532, 30.916, 34.886, 34.647, 7.9807, 8.0113,  7.955, 18.586, 45.395, 10.827,  14.72, 7.9135, 13.709, 7.0505, 7.0203, 15.581, 6.9989, 9.8914, 9.9055, 12.726, 17.588, 19.509,  17.55, 19.432, 5.1021, 5.1127, 50.848,   53.7, 14.608, 9.8449, 9.7846, 8.9387, 8.9368, 13.695,  8.891, 52.898, 15.632, 25.251, 10.877, 10.875, 6.0841, 24.231, 6.0411, 6.0474,  6.024, 6.0384, 6.0426, 16.652,  22.43, 14.621, 18.402, 34.894, 25.251, 19.497,  17.48, 13.674, 7.9687,  7.963,  13.75, 7.9781, 7.9464, 7.9281, 9.9252, 52.898, 9.8803, 9.8861, 9.8526, 18.389, 21.318,  22.24, 17.498, 17.545, 17.565, 10.855, 25.961,  10.84, 10.832, 18.441, 18.479, 42.532, 8.9309, 22.424, 16.629, 13.694,   53.7, 25.961, 14.623, 7.0185, 7.0429, 11.777,  7.015,      7, 7.0121, 11.848,   7.02, 14.727, 11.811,     27, 6.9812, 31.893, 21.318, 18.441, 18.479, 33.549, 94.853, 18.417, 5.1199, 5.1213, 5.1228, 5.0902, 9.8711,  22.29, 15.625, 5.1153, 5.1161, 5.1122, 33.698, 5.0842, 18.417, 15.554,  5.093, 5.0908, 5.0867, 5.0819, 23.108,  5.063, 22.424, 50.848, 20.342, 14.554, 49.109, 33.516, 21.397, 10.857, 10.877, 10.814, 66.966,  24.25, 7.9436, 23.108, 24.147, 19.497, 9.9146, 20.422, 30.003, 34.647, 34.894, 16.535, 17.548, 22.374, 45.395, 6.9705, 16.614, 7.9467, 15.588, 15.625, 12.708, 8.9116, 17.429,  22.43, 33.501, 11.792, 24.147, 94.853, 13.694, 33.698, 66.966, 14.554, 20.422, 14.727, 19.509,  6.039, 6.0477, 6.0128, 18.576, 12.761, 18.402, 15.518, 7.0172, 7.0289, 94.853, 66.966,  7.006, 18.576,  22.27, 8.9241, 30.003, 49.109, 66.966,     27, 18.389, 17.565,  11.81, 11.859, 21.308, 17.429, 94.853,  22.27, 12.706, 16.533, 94.853, 8.0064, 16.652,     27, 31.893, 7.9707, 11.756, 15.554, 15.551, 7.9566, 17.498, 49.109, 8.9582, 8.9023, 8.9069, 49.109, 16.599, 30.916, 33.698, 8.8977, 20.422,  24.25, 94.853, 22.374, 21.308, 66.966, 12.758, 66.966,  22.29,  22.24, 11.859, 16.599, 34.886, 12.735, 13.723, 14.608, 13.694, 14.623, 15.585, 16.533, 21.308,   53.7, 17.548, 24.231, 31.893, 94.853, 33.698, 20.342, 23.108, 24.147, 30.003, 31.893, 12.792,  11.81, 12.761, 20.342, 11.807, 8.9159,   8.94,  24.25, 9.8655, 8.8977, 10.798, 10.857, 34.894, 16.629, 13.674, 11.848,  8.946,  22.27, 15.632, 30.003,  24.25, 21.397, 11.799, 12.708, 11.777, 15.554, 21.308, 20.339, 16.533, 15.518 ],
"Category": [ "Default", "Default", "Default", "Default", "Default", "Default", "Default", "Default", "Default", "Default", "Default", "Default", "Default", "Default", "Default", "Default", "Default", "Default", "Default", "Default", "Default", "Default", "Default", "Default", "Default", "Topic1", "Topic1", "Topic1", "Topic1", "Topic1", "Topic1", "Topic1", "Topic1", "Topic1", "Topic1", "Topic1", "Topic1", "Topic1", "Topic1", "Topic1", "Topic1", "Topic1", "Topic1", "Topic1", "Topic1", "Topic1", "Topic1", "Topic1", "Topic1", "Topic1", "Topic2", "Topic2", "Topic2", "Topic2", "Topic2", "Topic2", "Topic2", "Topic2", "Topic2", "Topic2", "Topic2", "Topic2", "Topic2", "Topic2", "Topic2", "Topic2", "Topic2", "Topic2", "Topic2", "Topic2", "Topic2", "Topic2", "Topic2", "Topic2", "Topic2", "Topic3", "Topic3", "Topic3", "Topic3", "Topic3", "Topic3", "Topic3", "Topic3", "Topic3", "Topic3", "Topic3", "Topic3", "Topic3", "Topic3", "Topic3", "Topic3", "Topic3", "Topic3", "Topic3", "Topic3", "Topic3", "Topic3", "Topic3", "Topic3", "Topic3", "Topic4", "Topic4", "Topic4", "Topic4", "Topic4", "Topic4", "Topic4", "Topic4", "Topic4", "Topic4", "Topic4", "Topic4", "Topic4", "Topic4", "Topic4", "Topic4", "Topic4", "Topic4", "Topic4", "Topic4", "Topic4", "Topic4", "Topic4", "Topic4", "Topic4", "Topic5", "Topic5", "Topic5", "Topic5", "Topic5", "Topic5", "Topic5", "Topic5", "Topic5", "Topic5", "Topic5", "Topic5", "Topic5", "Topic5", "Topic5", "Topic5", "Topic5", "Topic5", "Topic5", "Topic5", "Topic5", "Topic5", "Topic5", "Topic5", "Topic5", "Topic6", "Topic6", "Topic6", "Topic6", "Topic6", "Topic6", "Topic6", "Topic6", "Topic6", "Topic6", "Topic6", "Topic6", "Topic6", "Topic6", "Topic6", "Topic6", "Topic6", "Topic6", "Topic6", "Topic6", "Topic6", "Topic6", "Topic6", "Topic6", "Topic6", "Topic7", "Topic7", "Topic7", "Topic7", "Topic7", "Topic7", "Topic7", "Topic7", "Topic7", "Topic7", "Topic7", "Topic7", "Topic7", "Topic7", "Topic7", "Topic7", "Topic7", "Topic7", "Topic7", "Topic7", "Topic7", "Topic7", "Topic7", "Topic7", "Topic7", "Topic8", "Topic8", "Topic8", "Topic8", "Topic8", "Topic8", "Topic8", "Topic8", "Topic8", "Topic8", "Topic8", "Topic8", "Topic8", "Topic8", "Topic8", "Topic8", "Topic8", "Topic8", "Topic8", "Topic8", "Topic8", "Topic8", "Topic8", "Topic8", "Topic8", "Topic9", "Topic9", "Topic9", "Topic9", "Topic9", "Topic9", "Topic9", "Topic9", "Topic9", "Topic9", "Topic9", "Topic9", "Topic9", "Topic9", "Topic9", "Topic9", "Topic9", "Topic9", "Topic9", "Topic9", "Topic9", "Topic9", "Topic9", "Topic9", "Topic9", "Topic10", "Topic10", "Topic10", "Topic10", "Topic10", "Topic10", "Topic10", "Topic10", "Topic10", "Topic10", "Topic10", "Topic10", "Topic10", "Topic10", "Topic10", "Topic10", "Topic10", "Topic10", "Topic10", "Topic10", "Topic10", "Topic10", "Topic10", "Topic10", "Topic10", "Topic11", "Topic11", "Topic11", "Topic11", "Topic11", "Topic11", "Topic11", "Topic11", "Topic11", "Topic11", "Topic11", "Topic11", "Topic11", "Topic11", "Topic11", "Topic11", "Topic11", "Topic11", "Topic11", "Topic11", "Topic11", "Topic11", "Topic11", "Topic11", "Topic11", "Topic12", "Topic12", "Topic12", "Topic12", "Topic12", "Topic12", "Topic12", "Topic12", "Topic12", "Topic12", "Topic12", "Topic12", "Topic12", "Topic12", "Topic12", "Topic12", "Topic12", "Topic12", "Topic12", "Topic12", "Topic12", "Topic12", "Topic12", "Topic12", "Topic12", "Topic13", "Topic13", "Topic13", "Topic13", "Topic13", "Topic13", "Topic13", "Topic13", "Topic13", "Topic13", "Topic13", "Topic13", "Topic13", "Topic13", "Topic13", "Topic13", "Topic13", "Topic13", "Topic13", "Topic13", "Topic13", "Topic13", "Topic13", "Topic13", "Topic13", "Topic14", "Topic14", "Topic14", "Topic14", "Topic14", "Topic14", "Topic14", "Topic14", "Topic14", "Topic14", "Topic14", "Topic14", "Topic14", "Topic14", "Topic14", "Topic14", "Topic14", "Topic14", "Topic14", "Topic14", "Topic14", "Topic14", "Topic14", "Topic14", "Topic14", "Topic15", "Topic15", "Topic15", "Topic15", "Topic15", "Topic15", "Topic15", "Topic15", "Topic15", "Topic15", "Topic15", "Topic15", "Topic15", "Topic15", "Topic15", "Topic15", "Topic15", "Topic15", "Topic15", "Topic15", "Topic15", "Topic15", "Topic15", "Topic15", "Topic15", "Topic16", "Topic16", "Topic16", "Topic16", "Topic16", "Topic16", "Topic16", "Topic16", "Topic16", "Topic16", "Topic16", "Topic16", "Topic16", "Topic16", "Topic16", "Topic16", "Topic16", "Topic16", "Topic16", "Topic16", "Topic16", "Topic16", "Topic16", "Topic16", "Topic16", "Topic17", "Topic17", "Topic17", "Topic17", "Topic17", "Topic17", "Topic17", "Topic17", "Topic17", "Topic17", "Topic17", "Topic17", "Topic17", "Topic17", "Topic17", "Topic17", "Topic17", "Topic17", "Topic17", "Topic17", "Topic17", "Topic17", "Topic17", "Topic17", "Topic17", "Topic1", "Topic2", "Topic5", "Topic3", "Topic12", "Topic10", "Topic6", "Topic2", "Topic3", "Topic6", "Topic15", "Topic3", "Topic6", "Topic11", "Topic1", "Topic2", "Topic4", "Topic6", "Topic13", "Topic3", "Topic1", "Topic3", "Topic4", "Topic11", "Topic3", "Topic6", "Topic11", "Topic2", "Topic2", "Topic3", "Topic3", "Topic9", "Topic9", "Topic4", "Topic5", "Topic14", "Topic15", "Topic16", "Topic1", "Topic8", "Topic11", "Topic11", "Topic14", "Topic7", "Topic2", "Topic6", "Topic1", "Topic1", "Topic3", "Topic10", "Topic10", "Topic14", "Topic14", "Topic14", "Topic1", "Topic2", "Topic10", "Topic17", "Topic2", "Topic9", "Topic6", "Topic11", "Topic15", "Topic4", "Topic5", "Topic6", "Topic8", "Topic10", "Topic13", "Topic1", "Topic6", "Topic11", "Topic11", "Topic14", "Topic12", "Topic12", "Topic5", "Topic3", "Topic4", "Topic8", "Topic3", "Topic5", "Topic7", "Topic8", "Topic4", "Topic5", "Topic9", "Topic8", "Topic6", "Topic7", "Topic10", "Topic12", "Topic16", "Topic9", "Topic1", "Topic1", "Topic3", "Topic3", "Topic4", "Topic5", "Topic6", "Topic6", "Topic6", "Topic8", "Topic10", "Topic13", "Topic4", "Topic4", "Topic5", "Topic8", "Topic8", "Topic12", "Topic13", "Topic2", "Topic2", "Topic2", "Topic4", "Topic4", "Topic5", "Topic7", "Topic7", "Topic7", "Topic8", "Topic10", "Topic10", "Topic11", "Topic13", "Topic4", "Topic5", "Topic13", "Topic14", "Topic16", "Topic16", "Topic1", "Topic11", "Topic12", "Topic17", "Topic7", "Topic8", "Topic7", "Topic2", "Topic2", "Topic12", "Topic15", "Topic1", "Topic13", "Topic4", "Topic10", "Topic12", "Topic3", "Topic7", "Topic1", "Topic8", "Topic8", "Topic14", "Topic3", "Topic6", "Topic9", "Topic17", "Topic1", "Topic4", "Topic5", "Topic5", "Topic10", "Topic13", "Topic16", "Topic1", "Topic8", "Topic9", "Topic12", "Topic8", "Topic11", "Topic13", "Topic14", "Topic14", "Topic15", "Topic8", "Topic9", "Topic15", "Topic15", "Topic16", "Topic2", "Topic4", "Topic7", "Topic16", "Topic3", "Topic3", "Topic4", "Topic8", "Topic11", "Topic1", "Topic8", "Topic2", "Topic5", "Topic13", "Topic16", "Topic16", "Topic16", "Topic3", "Topic5", "Topic6", "Topic10", "Topic12", "Topic3", "Topic13", "Topic5", "Topic2", "Topic5", "Topic6", "Topic7", "Topic2", "Topic6", "Topic11", "Topic16", "Topic9", "Topic13", "Topic14", "Topic17", "Topic5", "Topic6", "Topic11", "Topic11", "Topic6", "Topic8", "Topic13", "Topic14", "Topic15", "Topic2", "Topic9", "Topic10", "Topic1", "Topic2", "Topic5", "Topic7", "Topic12", "Topic10", "Topic13", "Topic2", "Topic3", "Topic14", "Topic10", "Topic7", "Topic9", "Topic12", "Topic13", "Topic13", "Topic13", "Topic9", "Topic14", "Topic5", "Topic9", "Topic11", "Topic15", "Topic6", "Topic14", "Topic14", "Topic5", "Topic7", "Topic8", "Topic1", "Topic1", "Topic2", "Topic3", "Topic3", "Topic3", "Topic3", "Topic4", "Topic4", "Topic4", "Topic5", "Topic5", "Topic6", "Topic6", "Topic8", "Topic8", "Topic8", "Topic10", "Topic10", "Topic11", "Topic11", "Topic11", "Topic11", "Topic14", "Topic14", "Topic15", "Topic16", "Topic17", "Topic17", "Topic17" ] 
},
"token.table": {
 "Term": [ "abandoned", "acc", "access", "access", "accommodation", "act", "advice", "affected", "aftermath", "aftermath", "aftershock", "aftershock", "aftershock", "aftershock", "aftershocks", "aftershocks", "aftershocks", "aftershocks", "airport", "allowed", "ami", "ami", "amount", "amount", "anderton", "anglican", "anniversary", "announced", "announced", "announced", "announcement", "answers", "apology", "appears", "appears", "appointed", "architecture", "area", "area", "area", "area", "areas", "areas", "arm", "arm", "armchair", "arms", "arms", "arrive", "asked", "asked", "asks", "asks", "asks", "asks", "assessment", "assessments", "assets", "assistance", "assistance", "astrologer", "athletes", "auckland", "auckland", "auckland", "authority", "awaited", "axe", "baby", "back", "back", "back", "background", "background", "badly", "badly", "badly", "balanced", "ball", "ball", "ball", "band", "bank", "barrier", "bed", "beginning", "benchmark", "big", "big", "bill", "bill", "billion", "bin", "black", "black", "black", "black", "blah", "blue", "board", "bob", "bob", "body", "bollard", "bounds", "box", "box", "boy", "boy", "break", "broken", "broken", "broken", "broken", "brought", "brown", "brownlee", "budget", "build", "build", "builders", "building", "building", "building", "building", "buildings", "buildings", "buildings", "burns", "business", "business", "businesses", "businesses", "called", "called", "called", "calling", "camping", "cancelled", "candle", "cantabrians", "cantabrians", "capsule", "capsules", "car", "car", "car", "car", "card", "cardboard", "carrying", "carrying", "carrying", "carrying", "carrying", "cat", "cat", "catastrophe", "cathedral", "cathedral", "caused", "caused", "caused", "caused", "cbd", "cbd", "cent", "central", "central", "centre", "centre", "centre", "centre", "ceo", "ceo", "cera", "cera", "chamber", "chats", "chch", "chch", "chch", "check", "chemical", "chemical", "chief", "children", "children", "children", "children", "chim", "chimneys", "city", "city", "city", "city", "city", "city", "city", "claims", "claims", "clown", "clutching", "coast", "coast", "collapse", "collapsing", "colours", "coming", "coming", "comments", "comments", "comments", "commerce", "commission", "commonwealth", "community", "companies", "companies", "company", "concern", "concern", "conditions", "conditions", "container", "containers", "contents", "continue", "continuing", "continuing", "continuing", "continuing", "contractors", "controversial", "cordon", "corner", "cost", "cost", "cost", "cost", "costs", "council", "council", "councils", "couple", "couple", "couple", "couple", "couple", "cover", "crack", "crack", "cracked", "cracked", "cracks", "cricket", "cross", "cross", "crowd", "crowd", "crushed", "cup", "cup", "cut", "cut", "cut", "dalai", "damage", "damage", "damage", "damage", "damage", "damage", "damaged", "damaged", "damaged", "damaged", "date", "day", "day", "day", "deal", "dear", "dear", "debate", "debris", "debris", "debris", "december", "december", "decision", "decision", "declared", "deep", "deep", "delhi", "demolished", "demolishing", "demolishing", "demolition", "demolition", "depicts", "depicts", "depicts", "devastating", "devastating", "devastating", "developed", "disaster", "disasters", "district", "district", "dog", "donations", "door", "door", "door", "dressed", "drinking", "driver", "due", "due", "ears", "earth", "earth", "economy", "economy", "edge", "efforts", "election", "elections", "elections", "elections", "empowers", "end", "end", "end", "end", "end", "english", "enormous", "enormous", "eqc", "eqc", "estate", "evans", "events", "events", "executive", "explains", "extra", "face", "face", "face", "facilities", "faction", "false", "fanzone", "fanzone", "father", "fault", "fear", "fear", "feet", "fence", "fence", "fight", "figure", "finance", "finance", "financial", "financial", "fires", "fissure", "flag", "flag", "flag", "fleeing", "floods", "flush", "foreign", "form", "foundation", "founder", "frames", "frames", "frames", "friend", "friend", "front", "front", "frustrated", "full", "full", "fund", "future", "gambling", "games", "games", "gas", "gerry", "giant", "giving", "godley", "goff", "gold", "government", "government", "government", "governor", "grand", "great", "great", "green", "greener", "ground", "ground", "ground", "ground", "ground", "group", "group", "group", "hand", "hand", "hand", "hand", "hand", "hands", "hands", "happen", "harbour", "head", "head", "head", "head", "head", "heading", "heading", "heading", "heading", "heading", "heading", "headline", "headline", "headlines", "heart", "heavy", "helping", "helping", "heritage", "heritage", "heritage", "heritage", "high", "high", "high", "high", "high", "historic", "historic", "hit", "hit", "hit", "hit", "hits", "ho", "hobbit", "holding", "holding", "holding", "holds", "holds", "holds", "holds", "home", "home", "home", "homeowners", "homes", "homes", "host", "hotel", "hotel", "hour", "house", "house", "house", "house", "house", "houses", "houses", "houses", "huge", "huge", "huge", "huge", "humour", "husband", "husband", "ideas", "impact", "impact", "impact", "includes", "includes", "including", "including", "including", "increase", "infrastructure", "infrastructure", "infrastructure", "insurance", "insurance", "interest", "international", "interviewed", "interviewed", "island", "island", "issues", "japan", "japan", "jersey", "jim", "john", "john", "john", "john", "june", "june", "june", "june", "katene", "ken", "key", "key", "kids", "kit", "kiwi", "kiwi", "kiwifruit", "label", "labeled", "lama", "lamb", "land", "land", "land", "land", "large", "large", "large", "large", "late", "latest", "lead", "lead", "leader", "leader", "leaky", "leaving", "left", "left", "left", "letter", "levy", "life", "light", "light", "light", "lightning", "limbo", "limbo", "liquefaction", "liquefaction", "liquefaction", "list", "list", "list", "live", "local", "local", "lower", "lower", "lunch", "lyttelton", "lyttelton", "made", "made", "made", "made", "made", "made", "make", "make", "make", "manchester", "map", "map", "map", "march", "march", "march", "march", "marryatt", "massive", "massive", "matches", "mayor", "mayor", "mayor", "mayoral", "mccully", "men", "men", "merivale", "milk", "million", "mine", "mine", "minutes", "mobile", "money", "months", "months", "months", "months", "months", "moon", "mother", "move", "move", "move", "move", "moved", "mp", "mp", "mud", "murray", "named", "named", "nature", "nature", "nature", "needed", "neighbour", "neighbours", "neighbours", "newcomer", "news", "news", "news", "newspaper", "newspaper", "night", "night", "night", "north", "north", "nuclear", "number", "number", "number", "nz", "nz", "nz", "october", "october", "october", "ongoing", "orange", "orange", "otago", "owner", "owners", "paid", "panel", "panel", "paper", "paper", "park", "parker", "parker", "parking", "part", "part", "parts", "parts", "party", "party", "party", "pay", "pay", "people", "people", "people", "people", "people", "people", "people", "people", "people", "perspective", "phil", "pike", "pike", "pile", "pile", "pipes", "pit", "place", "place", "plan", "plan", "plan", "planking", "planning", "plastic", "plumbing", "pm", "pm", "point", "point", "point", "pointing", "policies", "politicians", "port", "port", "portaloo", "portaloos", "pours", "power", "power", "power", "powers", "powers", "predict", "prediction", "predictions", "premises", "premiums", "press", "prime", "prime", "prince", "prince", "printed", "printed", "priority", "problems", "problems", "problems", "problems", "problems", "profile", "proof", "properties", "prostitutes", "protest", "public", "public", "public", "published", "quakes", "queue", "rail", "rain", "rain", "rate", "rate", "rats", "reach", "reaction", "reading", "reading", "reading", "reading", "rebuild", "rebuild", "rebuild", "rebuild", "rebuilding", "rebuilding", "rebuilding", "rebuilding", "rebuilding", "rebuilt", "receivership", "recently", "recession", "reconstruction", "reconstruction", "recovery", "red", "red", "referring", "refugees", "refugees", "region", "reinsurance", "remember", "repair", "replaced", "replies", "replies", "replies", "replies", "report", "report", "report", "reported", "representing", "representing", "representing", "representing", "representing", "represents", "represents", "represents", "represents", "represents", "rescue", "rescue", "reserve", "residential", "residential", "residents", "residents", "residents", "residents", "result", "retrieve", "ride", "ring", "ring", "rise", "rise", "risk", "rival", "rival", "river", "river", "river", "road", "road", "road", "road", "roads", "robert", "rock", "rolling", "royal", "rubbish", "rubble", "rubble", "rubble", "rubble", "rugby", "rwc", "sand", "santa", "santa", "scale", "scf", "search", "security", "seismograph", "sense", "septic", "series", "sewage", "sewer", "sewerage", "sewerage", "shake", "shaking", "ship", "shipping", "shop", "shop", "short", "shoulder", "shouts", "shouts", "shouts", "shovel", "show", "show", "show", "show", "show", "shown", "shown", "sign", "sign", "sign", "signpost", "signpost", "silence", "simon", "simply", "sit", "sits", "sits", "sits", "sits", "size", "small", "small", "smith", "snow", "south", "south", "southland", "spade", "spade", "spade", "special", "spending", "spirit", "spirit", "spite", "stadium", "stand", "stand", "stand", "stand", "standing", "standing", "standing", "standing", "standing", "stands", "stands", "stands", "stands", "star", "state", "statue", "stickered", "stone", "stone", "stop", "stop", "stops", "streets", "stress", "strike", "strong", "struggles", "suburbs", "suffered", "suffered", "suggesting", "suggesting", "suggests", "suggests", "suggests", "survivors", "system", "talking", "tape", "tax", "tea", "team", "tear", "tear", "television", "tells", "tells", "tells", "tells", "temporary", "thinks", "thinks", "thought", "thumbs", "time", "time", "time", "title", "title", "title", "today", "today", "toilet", "toilet", "toilets", "tony", "tools", "tower", "tracks", "trapped", "treasury", "trouble", "truck", "true", "tsunami", "tsunami", "tuesday", "tunnel", "tv", "tv", "urban", "venue", "version", "version", "version", "victims", "visit", "voice", "voice", "volcanic", "volcano", "wagner", "waka", "walk", "walks", "walks", "wallet", "water", "water", "water", "wave", "wearing", "wearing", "wearing", "wearing", "wears", "weather", "weather", "week", "week", "week", "week", "week", "wife", "wife", "william", "win", "wire", "wondering", "wonders", "wonders", "wonders", "word", "word", "words", "words", "words", "work", "work", "work", "workers", "workers", "workers", "working", "working", "working", "working", "workman", "world", "worst", "year", "year", "yellow", "zone", "zone", "zone", "zones", "zones" ],
"Topic": [ 9, 3, 6, 11, 7, 2, 15, 3, 16, 17, 1, 2, 4, 7, 4, 11, 14, 16, 8, 6, 1, 7, 7, 17, 17, 8, 5, 2, 3, 6, 12, 14, 8, 11, 16, 8, 10, 1, 6, 14, 15, 9, 14, 2, 5, 3, 7, 9, 14, 5, 9, 9, 11, 12, 16, 6, 10, 9, 3, 14, 4, 13, 2, 9, 12, 9, 6, 2, 3, 9, 13, 15, 2, 5, 5, 6, 8, 11, 5, 7, 9, 4, 11, 6, 3, 6, 11, 4, 15, 2, 9, 2, 13, 3, 4, 5, 14, 12, 14, 3, 8, 17, 17, 11, 6, 10, 13, 12, 16, 7, 2, 5, 11, 13, 10, 2, 9, 2, 9, 16, 10, 5, 10, 12, 15, 5, 12, 14, 6, 6, 11, 3, 6, 4, 8, 12, 8, 1, 1, 13, 4, 5, 5, 5, 3, 12, 14, 17, 2, 11, 2, 7, 10, 13, 15, 9, 11, 3, 5, 8, 1, 5, 7, 16, 6, 8, 11, 6, 14, 1, 2, 7, 14, 1, 15, 6, 9, 15, 14, 2, 7, 15, 13, 11, 13, 15, 2, 3, 4, 10, 15, 15, 5, 8, 10, 12, 14, 15, 16, 1, 4, 8, 13, 5, 17, 1, 14, 14, 1, 12, 3, 8, 9, 15, 10, 13, 5, 1, 3, 1, 4, 16, 13, 15, 10, 10, 13, 11, 4, 5, 11, 14, 10, 15, 6, 14, 2, 7, 11, 15, 2, 8, 15, 1, 3, 5, 6, 9, 17, 1, 1, 17, 1, 17, 17, 3, 2, 15, 8, 10, 3, 7, 14, 3, 11, 12, 16, 1, 5, 6, 7, 12, 13, 3, 5, 6, 10, 5, 4, 6, 9, 15, 3, 10, 5, 7, 9, 12, 4, 15, 3, 7, 8, 6, 16, 13, 6, 6, 9, 2, 9, 8, 10, 17, 3, 5, 16, 10, 7, 1, 6, 17, 15, 3, 1, 13, 16, 16, 4, 13, 2, 9, 14, 2, 10, 7, 11, 4, 9, 17, 2, 9, 17, 9, 2, 3, 4, 10, 13, 2, 1, 5, 6, 10, 10, 14, 1, 2, 15, 12, 10, 4, 6, 7, 13, 4, 12, 7, 11, 16, 11, 4, 13, 9, 3, 12, 17, 11, 1, 2, 2, 4, 1, 11, 1, 11, 14, 4, 1, 16, 3, 15, 10, 5, 2, 4, 12, 9, 10, 10, 12, 6, 4, 10, 2, 10, 12, 7, 13, 10, 9, 5, 7, 5, 2, 17, 2, 6, 8, 11, 9, 4, 11, 14, 14, 2, 5, 12, 13, 17, 3, 14, 16, 3, 5, 7, 13, 15, 6, 12, 6, 16, 2, 3, 4, 9, 16, 1, 2, 10, 11, 12, 13, 3, 13, 11, 5, 1, 5, 17, 5, 10, 12, 17, 8, 9, 11, 13, 17, 5, 11, 1, 2, 3, 6, 11, 11, 2, 3, 7, 17, 2, 3, 11, 14, 1, 10, 13, 6, 6, 12, 7, 9, 10, 10, 2, 6, 10, 13, 14, 5, 6, 11, 1, 4, 9, 11, 4, 3, 13, 16, 2, 4, 11, 8, 10, 4, 8, 10, 8, 2, 10, 13, 1, 11, 11, 8, 12, 17, 1, 16, 6, 3, 5, 14, 17, 2, 5, 9, 11, 1, 4, 6, 16, 16, 4, 2, 9, 4, 10, 3, 5, 7, 14, 10, 16, 16, 2, 4, 6, 9, 4, 6, 8, 11, 14, 4, 1, 9, 2, 17, 12, 12, 6, 7, 11, 2, 1, 15, 8, 13, 14, 1, 6, 9, 4, 14, 16, 1, 6, 15, 13, 14, 17, 6, 8, 4, 10, 16, 4, 9, 11, 14, 15, 16, 9, 11, 14, 14, 1, 3, 16, 2, 3, 4, 16, 15, 1, 15, 7, 2, 8, 17, 17, 8, 9, 12, 10, 11, 2, 7, 12, 3, 10, 15, 3, 6, 8, 9, 14, 4, 4, 6, 14, 15, 17, 2, 5, 17, 7, 2, 14, 17, 4, 9, 17, 10, 3, 5, 17, 14, 3, 8, 16, 3, 13, 13, 16, 17, 1, 16, 3, 4, 10, 12, 2, 5, 10, 7, 13, 17, 11, 6, 17, 1, 6, 6, 10, 3, 8, 3, 11, 8, 8, 17, 14, 6, 8, 2, 13, 2, 4, 17, 8, 15, 3, 4, 5, 6, 8, 10, 12, 14, 15, 3, 2, 7, 11, 11, 16, 13, 16, 2, 10, 8, 11, 13, 4, 3, 7, 13, 2, 5, 1, 11, 12, 9, 1, 14, 1, 3, 13, 13, 16, 1, 4, 12, 8, 9, 4, 4, 4, 6, 1, 14, 2, 9, 3, 16, 5, 15, 2, 3, 8, 10, 13, 15, 17, 10, 6, 14, 6, 9, 12, 15, 8, 1, 12, 12, 1, 11, 10, 11, 13, 2, 8, 3, 9, 11, 12, 2, 9, 10, 16, 2, 9, 10, 12, 16, 5, 1, 1, 11, 9, 14, 9, 6, 14, 16, 10, 12, 15, 1, 3, 11, 8, 8, 10, 12, 16, 6, 12, 13, 8, 1, 5, 6, 7, 11, 1, 6, 7, 11, 15, 5, 14, 11, 10, 14, 3, 12, 14, 16, 15, 6, 16, 4, 6, 8, 15, 12, 1, 17, 7, 10, 11, 1, 4, 16, 17, 11, 5, 10, 4, 16, 13, 5, 6, 11, 16, 7, 7, 16, 4, 15, 8, 1, 5, 6, 11, 9, 3, 16, 13, 13, 13, 16, 12, 4, 10, 10, 12, 14, 2, 11, 1, 8, 15, 17, 3, 7, 8, 9, 16, 1, 11, 7, 12, 17, 5, 9, 3, 12, 5, 3, 1, 3, 11, 14, 8, 13, 16, 3, 1, 1, 16, 15, 3, 11, 16, 8, 2, 5, 11, 4, 7, 2, 3, 4, 8, 6, 7, 10, 15, 17, 1, 3, 11, 12, 8, 11, 5, 14, 4, 5, 12, 15, 14, 14, 4, 17, 5, 7, 9, 5, 7, 4, 9, 9, 11, 17, 5, 13, 12, 6, 2, 3, 3, 4, 5, 3, 3, 9, 13, 14, 8, 3, 14, 13, 7, 2, 3, 5, 1, 8, 10, 3, 8, 11, 13, 13, 15, 6, 8, 8, 5, 2, 16, 13, 5, 1, 3, 3, 13, 7, 13, 5, 7, 1, 5, 8, 15, 16, 9, 10, 4, 6, 6, 7, 15, 1, 7, 2, 1, 10, 16, 15, 9, 13, 14, 17, 14, 1, 12, 3, 6, 8, 9, 10, 1, 3, 16, 17, 11, 12, 3, 5, 15, 4, 5, 1, 6, 11, 9, 10, 14, 5, 10, 14, 2, 12, 14, 15, 16, 7, 8, 1, 2, 14, 2, 6, 14, 6, 14 ],
"Freq": [ 0.96528, 0.93831, 0.87376, 0.12482, 0.9369, 0.93523, 0.94418, 0.96274, 0.33414, 0.66828, 0.056998, 0.17099, 0.56998, 0.22799, 0.57032, 0.33433, 0.039333, 0.058999, 0.96215, 0.98434, 0.66057, 0.36031, 0.82458, 0.16492, 1.0212, 0.93776, 0.94231, 0.42163, 0.084327, 0.50596, 0.94164, 0.94391, 0.96215, 0.78731, 0.22495, 0.96215, 0.98304, 0.22326, 0.55815, 0.11163, 0.11163, 0.27382, 0.68456, 0.12567, 0.87971, 0.93831, 0.78184, 0.19546, 0.96863, 0.31375, 0.6275, 0.17212, 0.11475, 0.34425, 0.40162, 0.9346, 0.94294, 0.94073, 0.16561, 0.82803, 0.98158, 0.96956, 0.78136, 0.078136, 0.15627, 0.98064, 0.9346, 0.93523, 0.93831, 0.32146, 0.51434, 0.19288, 0.28522, 0.71305, 0.75348, 0.12558, 0.12558, 0.94147, 0.44801, 0.51201, 0.064002, 0.98158, 1.0054, 0.9346, 0.97801, 0.9346, 0.94147, 0.56194, 0.44955, 0.66635, 0.30755, 0.94339, 0.9448, 0.2419, 0.2419, 0.12095, 0.42333, 0.94164, 0.96863, 0.93831, 0.32835, 0.68654, 1.0212, 0.94147, 0.9346, 0.78675, 0.19669, 0.10229, 0.92063, 0.9369, 0.044963, 0.49459, 0.17985, 0.26978, 0.94294, 0.93523, 0.99954, 0.99259, 0.19778, 0.79113, 0.94294, 0.24848, 0.37272, 0.33131, 0.082826, 0.57728, 0.31657, 0.11173, 0.9346, 0.91439, 0.053788, 0.3747, 0.6245, 0.46909, 0.093817, 0.46909, 0.93776, 0.93521, 0.93521, 0.9448, 0.78539, 0.19635, 0.94231, 0.94231, 0.14346, 0.28692, 0.14346, 0.43038, 0.95949, 0.98143, 0.23515, 0.39191, 0.078382, 0.23515, 0.078382, 0.72411, 0.24137, 0.96274, 0.54114, 0.48703, 0.12831, 0.44907, 0.25661, 0.19246, 0.54323, 0.47532, 0.94147, 0.8152, 0.2038, 0.46905, 0.078175, 0.3127, 0.15635, 0.19648, 0.78593, 0.20452, 0.74992, 0.96891, 0.96863, 0.29381, 0.39174, 0.34277, 0.98505, 0.85728, 0.14288, 1.0085, 0.10131, 0.10131, 0.60783, 0.20261, 0.99497, 0.99497, 0.1344, 0.17919, 0.014933, 0.11946, 0.16426, 0.23893, 0.1344, 0.73562, 0.27586, 0.9774, 0.9448, 0.31607, 0.63214, 0.98502, 0.94391, 1.0024, 0.12559, 0.87913, 0.39852, 0.56932, 0.056932, 0.94418, 0.98304, 0.96956, 0.96694, 0.70528, 0.30226,  1.012, 0.78676, 0.19669, 0.7568, 0.25227, 1.0013, 0.9936, 0.9448, 0.98143,  0.706, 0.064182, 0.12836, 0.12836, 0.94294, 0.94418, 0.99188, 0.94391, 0.73913, 0.056856, 0.11371, 0.11371, 0.97466, 0.34635, 0.66384, 0.95947, 0.5715, 0.05715, 0.05715, 0.1143, 0.2286, 0.98502, 0.78311, 0.22375, 0.31527, 0.63053, 1.0028, 0.93831, 0.78127, 0.19532, 0.78328, 0.22379, 0.93831, 0.95445, 0.053025, 0.14273, 0.71367, 0.14273, 0.99101, 0.10181, 0.18327, 0.1629, 0.28508, 0.081451, 0.20363, 0.13459, 0.44864, 0.17946, 0.26918, 0.94231, 0.73889, 0.092362, 0.18472, 0.94418, 0.71254, 0.28502, 0.98235,  0.196,  0.588,  0.196, 0.82716, 0.16543, 0.16904, 0.84518, 0.93776, 0.19751, 0.79004, 0.98505, 0.9346, 0.19586, 0.78344, 0.19589, 0.78355, 0.64621, 0.27695, 0.092316, 0.5608, 0.33648, 0.11216, 0.94294, 0.93793, 1.0065, 0.71225, 0.2849, 0.98438, 0.96274, 0.14324, 0.71621, 0.14324, 0.95027, 0.9416, 1.0034, 0.19589, 0.78355, 0.94391, 0.78106, 0.19526, 0.30363, 0.70848, 0.9416, 0.94073, 0.95119, 0.093206, 0.093206, 0.83885, 0.94073, 0.10136, 0.10136, 0.50682, 0.10136, 0.20273, 0.95527, 0.50805, 0.50805, 0.10144,  0.913, 0.94294, 0.96863, 0.16417, 0.82086, 1.0085, 0.96623, 0.94294, 0.75294, 0.12549, 0.12549, 0.96956, 0.9416, 0.94164, 0.78197, 0.19549, 0.99101, 0.98143, 0.78582, 0.19646, 0.96528, 0.14275, 0.85652, 1.0165, 0.99196, 0.40124, 0.57957, 0.78083, 0.19521, 0.93521, 0.96605, 0.1015, 0.20299, 0.71047, 0.9416, 0.98502, 0.95027, 0.93831, 0.94418, 0.98304, 0.94231, 0.39182, 0.47018, 0.15673, 0.62765, 0.31382, 0.28578, 0.71445, 0.97397, 0.25169, 0.75506, 0.93523, 0.98304, 0.94164, 0.64575,  0.369, 0.94294, 0.99551, 0.94231, 0.9369, 0.94231, 0.93523, 0.9763, 0.51585, 0.14329, 0.3439, 0.98143, 0.96528, 0.23573, 0.78577, 1.0024, 0.94391, 0.36291, 0.060486, 0.12097, 0.30243, 0.18146, 0.59438, 0.33965, 0.084912, 0.19249, 0.12832, 0.19249, 0.32081, 0.19249, 0.16514, 0.8257, 0.95882, 0.97533, 0.16961, 0.25441, 0.084804, 0.42402, 0.084804, 0.041367, 0.041367, 0.1241, 0.082734, 0.6205, 0.082734, 0.8024, 0.21884, 0.94147, 0.98235, 0.98502, 0.39525, 0.59287, 0.46306, 0.27783, 0.18522, 0.092611, 0.064303, 0.19291, 0.25721, 0.38582, 0.12861, 0.78573, 0.19643, 0.43066, 0.37683, 0.1615, 0.053833, 0.94147, 0.94147, 0.93523, 0.084621, 0.84621, 0.084621, 0.16951, 0.33903, 0.42378, 0.084757, 0.13679, 0.68394, 0.20518, 0.9346, 0.61547, 0.41031, 0.96124, 0.78489, 0.19622, 0.94294, 0.029676, 0.17805, 0.35611, 0.26708, 0.17805, 0.072726, 0.65454, 0.2909, 0.41238, 0.20619, 0.20619, 0.20619, 1.0169, 0.85466, 0.14244, 0.97533, 0.25092, 0.12546, 0.6273, 0.67182, 0.33591, 0.3141, 0.3141, 0.39263, 0.9774, 0.33664, 0.11221, 0.56107, 0.97181, 0.029449, 0.99196, 0.96215, 0.62987, 0.31493, 0.87295, 0.14549, 0.95882, 0.87711, 0.1253, 0.99468, 0.99201, 0.68289, 0.088115, 0.22029, 0.022029, 0.35756, 0.17878, 0.40225, 0.08939, 0.95027, 0.9345, 0.70535, 0.28214, 0.9416, 0.96761, 0.80878, 0.2022, 0.9369, 0.94391, 0.96761, 0.99101, 0.95027, 0.053811, 0.053811, 0.80716, 0.053811, 0.37626, 0.25084, 0.18813, 0.18813, 0.94391, 0.99978, 0.24096, 0.72287, 0.78246, 0.19562, 0.99215, 0.94164, 0.30069, 0.54123, 0.18041, 0.93523, 0.93521, 0.99497, 0.25177, 0.62944, 0.12589, 0.93521, 0.39118, 0.58678, 0.38948, 0.21638, 0.38948, 0.70993, 0.14199, 0.14199, 0.98505, 0.25361, 0.76084, 0.092008, 0.92008, 0.9416, 0.14405, 0.86432, 0.057208, 0.11442, 0.62929, 0.11442, 0.057208, 0.057208, 0.22455, 0.56136, 0.22455, 0.94391, 0.33557, 0.55928, 0.11186, 0.051461, 0.66899, 0.10292, 0.15438, 0.96524, 0.19648, 0.78593, 0.9369, 0.029807, 0.35768, 0.59614, 0.9763, 0.93776, 0.10138, 0.91242, 0.96761, 0.96605, 1.0065, 0.85306, 0.14218, 0.99607, 0.9936, 0.98438, 0.42349, 0.1694, 0.084698, 0.1694, 0.1694, 0.95038, 0.99978, 0.068857, 0.20657, 0.068857, 0.61971, 0.93523, 0.14416, 0.86498, 0.9369, 0.95949, 0.83002,  0.166, 0.62919, 0.25168, 0.12584, 0.94294, 0.96274, 0.78741, 0.19685, 0.94391, 0.68375, 0.22792, 0.056979, 0.77628, 0.22642, 0.7582, 0.12637, 0.12637, 0.7124, 0.28496, 0.99607, 0.27742, 0.18495, 0.55485, 0.2921, 0.14605, 0.5842, 0.11308, 0.22616, 0.67848, 0.96605, 0.80763, 0.20191, 0.93521, 0.95882, 1.0113, 0.98304, 0.44713, 0.55891, 0.29207, 0.73019, 0.9774, 0.35804, 0.6564, 0.96863, 0.59079,  0.422, 0.19659, 0.78637, 0.56028, 0.22411, 0.22411, 0.12858, 0.83576, 0.12651, 0.13705, 0.11597, 0.021085, 0.16868, 0.094884, 0.25302, 0.021085, 0.052713, 0.96274, 0.93523, 0.92986, 0.084532, 0.19782, 0.79126, 0.96956, 0.97533, 0.16536, 0.82681, 0.75205, 0.12534, 0.12534, 0.9416, 0.93831, 0.97647, 0.96956, 0.55266, 0.46055, 0.14605, 0.51117, 0.36512, 0.94073, 0.95947, 0.96863, 0.87391, 0.12484, 0.9603, 1.0176, 0.95027, 0.25095, 0.12547, 0.62737, 0.78244, 0.19561, 0.9416, 0.9416, 1.0102, 0.95882, 0.95947, 0.96863, 0.59404, 0.39603, 0.14394, 0.86366, 0.91341, 0.10149, 0.93523, 0.089806, 0.35922, 0.22451, 0.31432, 0.044903, 0.95119, 0.94294, 0.9346, 0.96863, 0.9346, 0.20315, 0.10158, 0.71103, 0.98785, 0.99831, 1.0102, 0.99215, 0.82181, 0.16436, 0.12571, 0.87995, 0.9448, 0.93523, 0.93776, 0.57776, 0.16508, 0.082538, 0.16508, 0.25926, 0.074075, 0.40741, 0.25926, 0.28159, 0.18773, 0.32852, 0.046931, 0.18773, 0.98235, 0.93521, 0.93521, 0.96605, 0.72459, 0.24153,  1.001, 0.4348, 0.56713, 0.95027, 0.078599, 0.86458, 0.94418, 0.93521, 0.93831, 1.0054, 0.9774, 0.054379, 0.16314, 0.48941, 0.32627, 0.73549, 0.18387, 0.091936, 0.96215, 0.36663, 0.29997, 0.03333, 0.16665, 0.16665, 0.23368, 0.046736, 0.42062, 0.23368, 0.093471, 0.78664, 0.22475, 0.99962, 0.19678, 0.78711, 0.2458, 0.44244, 0.2458, 0.09832, 0.94418, 0.9346, 0.95027, 0.85665, 0.11422, 0.36565, 0.65816, 0.98162, 0.31527, 0.63053, 0.6397, 0.31985, 0.06397, 0.19332, 0.25777, 0.38665, 0.19332, 0.96605, 0.96694, 1.0013, 0.9416, 0.97533, 0.98505, 0.46224, 0.03852, 0.03852, 0.42372, 1.0019, 0.97647, 0.95027, 0.16575, 0.82875, 0.9774, 0.93521, 0.96694, 0.95882, 0.94147, 0.94073, 0.93831, 1.0017, 1.0092, 0.9448, 0.78899, 0.19725, 0.96623, 0.99978, 0.98304, 1.0071, 0.72512, 0.24171, 0.93523, 0.96605, 0.16535, 0.16535, 0.66141, 0.95119, 0.14575, 0.36436, 0.29149, 0.14575, 0.072873, 0.30346, 0.70807, 0.1475, 0.68833, 0.1475, 0.31375, 0.6275, 0.97801, 0.94164, 0.94231, 0.93831, 0.18424, 0.64485, 0.092122, 0.092122, 0.96215, 0.3066, 0.71541, 0.93831, 1.0028, 0.90464, 0.08224, 0.94418, 0.16631, 0.16631, 0.66525, 1.0012, 0.97466, 0.85751, 0.14292, 0.9416, 1.0048, 0.55161, 0.091935, 0.091935, 0.2758, 0.054342, 0.3804, 0.10868, 0.054342, 0.43474, 0.48153, 0.24076, 0.18057, 0.12038, 0.93776,   1.01, 0.98235, 0.94391, 0.16546, 0.8273, 0.66206, 0.33103, 0.94391, 0.99468, 0.99212, 0.95119, 0.96694, 0.9369, 0.99115, 0.16465, 0.82324, 0.16522, 0.82609, 0.33699, 0.56165, 0.11233, 0.99289, 0.96956, 0.98162, 0.98434, 0.93523, 0.99607, 0.93831, 0.71429, 0.28572, 0.96274, 0.13677, 0.41032, 0.34193, 0.13677, 0.93776, 0.71276, 0.2851, 0.9448, 0.9369, 0.22794, 0.45589, 0.34191, 0.16933, 0.59265, 0.25399, 0.71135, 0.28454, 0.54297, 0.48867, 1.0092, 0.93727, 0.95882, 0.93776, 0.96215, 0.98235, 0.97466, 0.95027, 0.9448, 0.94231, 0.40345, 0.60517, 0.97801, 0.9448, 0.78254, 0.19563, 0.94231, 0.96124, 0.18681, 0.046703, 0.74724, 1.0027, 0.97533, 0.16553, 0.82766, 0.9416, 0.9346, 0.9346, 0.9369, 0.94418, 0.85101, 0.14183, 0.95949, 0.42532, 0.17013, 0.42532, 0.94418, 0.068711, 0.20613, 0.41227, 0.34356, 0.99468, 0.90648, 0.10072, 0.36147, 0.060244, 0.42171, 0.060244, 0.12049, 0.092068, 0.92068, 0.99101, 0.9763, 0.96605, 0.94164, 0.16559, 0.16559, 0.66236, 0.54227, 0.48804, 0.44595, 0.49054, 0.08919, 0.23607, 0.47213, 0.31475, 0.47221, 0.31481, 0.2361, 0.25136, 0.12568, 0.50273, 0.12568, 0.95027, 0.97894, 0.93776, 0.75326, 0.21522, 0.9841, 0.05733, 0.77395, 0.17199, 0.16549, 0.82745 ] 
},
"R":     25,
"lambda.step":   0.01,
"plot.opts": {
 "xlab": "PC1",
"ylab": "PC2" 
},
"topic.order": [ 8, 12, 2, 5, 15, 13, 1, 17, 11, 4, 10, 3, 9, 7, 14, 6, 16 ] 
}